[
    {
      "text": "A rose by any other name would smell as sweet.",
      "author": "William Shakespeare"
    },
    {
      "text": "All that glitters is not gold.",
      "author": "William Shakespeare"
    },
    {
      "text": "All the world’s a stage, and all the men and women merely players.",
      "author": "William Shakespeare"
    },
    {
        "text": "Eighty percent of success is showing up.",
        "author": "Woody Allen"
    },
    {
        "text": "Genius is one percent inspiration and ninety-nine percent perspiration.",
        "author": "Thomas Edison"
    },
    {
      "text": "He travels the fastest who travels alone.",
      "author": "Rudyard Kipling"
    },
    {
      "text": "Hell has no fury like a woman scorned.",
      "author": "William Congreve"
    },
    {
      "text": "If you are going through hell, keep going.",
      "author": "Winston Churchill"
    },
    {
      "text": "If you want something done right, do it yourself.",
      "author": "Charles-Guillaume Étienne"
    },
    {
      "text": "Knowledge is power.",
      "author": "Sir Francis Bacon"
    },
    {
      "text": "No one can make you feel inferior without your consent.",
      "author": "Eleanor Roosevelt"
    },
    {
      "text": "Not all those who wander are lost.",
      "author": "J. R. R. Tolkein"
    },
    {
      "text": "Nothing is certain except for death and taxes.",
      "author": "Benjamin Franklin"
    },
    {
      "text": "Parting is such sweet sorrow.",
      "author": "William Shakespeare"
    },
    {
      "text": "Power corrupts; absolute power corrupts absolutely.",
      "author": "John Dalberg-Acton"
    },
    {
      "text": "Speak softly and carry a big stick.",
        "author": "Theodore Roosevelt"
    },
    {
      "text": "That’s one small step for a man, a giant leap for mankind.",
      "author": "Neil Armstrong"
    },
    {
      "text": "The only thing we have to fear is fear itself.",
      "author": "Franklin D. Roosevelt"
    },
    {
      "text": "Three can keep a secret, if two of them are dead.",
      "author": "Benjamin Franklin"
    },
    {
      "text": "The way to get started is to quit talking and begin doing.",
      "author": "Walt Disney"
    },
    {
      "text": "Life is what happens when you're busy making other plans",
      "author": "John Lennon"
    },
    {
      "text": "It is during our darkest moments that we must focus to see the light.",
      "author": "Aristotle"
    },
    {
      "text": "Whoever is happy will make others happy too.",
        "author": "Anne Frank"
    },
    {
      "text": "Do not go where the path may lead, go instead where there is no path and leave a trail.",
      "author": "Ralph Waldo Emerson"
    },
    {
      "text": "Whoever is happy will make others happy too.",
      "author": "Anne Frank"
    },
    {
      "text": "The greatest glory in living lies not in never falling, but in rising every time we fall.",
      "author": "Nelson Mandela"
    },
    {
      "text": "Life is really simple, but we insist on making it complicated.",
      "author": "Confucius"
    },
    {
      "text": "Life is ours to be spent, not to be saved.",
      "author": "D. H. Lawrence"
    }
  ]